LICENSE
README.md
build/examples/forage.cpp
build/lib.macosx-11.0-arm64-cpython-311/puffergrid/action.cpython-311-darwin.so
build/lib.macosx-11.0-arm64-cpython-311/puffergrid/event.cpython-311-darwin.so
build/lib.macosx-11.0-arm64-cpython-311/puffergrid/examples/forage.cpython-311-darwin.so
build/lib.macosx-11.0-arm64-cpython-311/puffergrid/grid.cpython-311-darwin.so
build/lib.macosx-11.0-arm64-cpython-311/puffergrid/grid_env.cpython-311-darwin.so
build/lib.macosx-11.0-arm64-cpython-311/puffergrid/grid_object.cpython-311-darwin.so
build/lib.macosx-11.0-arm64-cpython-311/puffergrid/observation_encoder.cpython-311-darwin.so
build/lib.macosx-11.0-arm64-cpython-311/puffergrid/stats_tracker.cpython-311-darwin.so
build/puffergrid/action.cpp
build/puffergrid/event.cpp
build/puffergrid/event.hpp
build/puffergrid/grid.cpp
build/puffergrid/grid.hpp
build/puffergrid/grid_env.cpp
build/puffergrid/grid_object.cpp
build/puffergrid/grid_object.hpp
build/puffergrid/observation_encoder.cpp
build/puffergrid/stats_tracker.cpp
examples/__init__.py
examples/forage.pyx
puffergrid/__init__.py
puffergrid/action.cpython-311-darwin.so
puffergrid/action.pxd
puffergrid/action.pyx
puffergrid/event.cpython-311-darwin.so
puffergrid/event.hpp
puffergrid/event.pxd
puffergrid/event.pyx
puffergrid/examples/forage.cpython-311-darwin.so
puffergrid/grid.cpp
puffergrid/grid.cpython-311-darwin.so
puffergrid/grid.hpp
puffergrid/grid.pxd
puffergrid/grid_env.cpython-311-darwin.so
puffergrid/grid_env.pxd
puffergrid/grid_env.pyx
puffergrid/grid_object.cpython-311-darwin.so
puffergrid/grid_object.hpp
puffergrid/grid_object.pxd
puffergrid/grid_object.pyx
puffergrid/observation_encoder.cpython-311-darwin.so
puffergrid/observation_encoder.pxd
puffergrid/observation_encoder.pyx
puffergrid/stats_tracker.cpython-311-darwin.so
puffergrid/stats_tracker.pxd
puffergrid/stats_tracker.pyx
puffergrid/wrappers/__init__.py
puffergrid/wrappers/grid_env_wrapper.py
setup.py
test_perf.py
puffergrid-0.0.8.dist-info/LICENSE
puffergrid-0.0.8.dist-info/METADATA
puffergrid-0.0.8.dist-info/WHEEL
puffergrid-0.0.8.dist-info/RECORD
