Metadata-Version: 2.1
Name: puffergrid
Version: 0.0.8
Summary: A framework for fast grid-based environments
Home-page: https://daveey.github.io
License: MIT
Keywords: puffergrid,gridworld,minigrid,rl,reinforcement-learning,environment,gym
Author: David Bloomin
Author-email: daveey@gmail.com
Requires-Python: >=3.10,<4.0
Classifier: License :: OSI Approved :: MIT License
Classifier: Programming Language :: Python :: 3
Classifier: Programming Language :: Python :: 3.10
Classifier: Programming Language :: Python :: 3.11
Classifier: Programming Language :: Python :: 3.12
Requires-Dist: cython (>=3.0.11,<4.0.0)
Requires-Dist: numpy (>=1.21.0,<2.0.0)
Project-URL: Repository, https://github.com/daveey/puffergrid
